{
  "client_id": "https://snake.ewancroft.uk/client-metadata.json",
  "client_name": "Atproto Snake",
  "client_uri": "https://snake.ewancroft.uk",
  "logo_uri": "https://snake.ewancroft.uk/favicon.png",
  "redirect_uris": [
    "https://snake.ewancroft.uk/auth/callback",
    "https://atproto-snake.vercel.app/auth/callback",
    "http://localhost:5173/auth/callback",
    "http://127.0.0.1:5173/auth/callback"
  ],
  "scope": "atproto",
  "grant_types": ["authorization_code", "refresh_token"],
  "response_types": ["code"],
  "token_endpoint_auth_method": "none",
  "application_type": "web",
  "dpop_bound_access_tokens": true
}